shenko/__init__.py
shenko/shenko.py
shenko/assets/audio/beep.ogg
shenko/assets/audio/click.ogg
shenko/assets/audio/click.wav
shenko/assets/images/logo.png
shenko/s00_init/__init__.py
shenko/s00_init/menu.py
shenko/utils/__init__.py
shenko/utils/assets.py
shenko/utils/logger.py
shenko/utils/ui.py
shenko-0.1.90.dist-info/AUTHORS.rst
shenko-0.1.90.dist-info/LICENSE
shenko-0.1.90.dist-info/METADATA
shenko-0.1.90.dist-info/WHEEL
shenko-0.1.90.dist-info/entry_points.txt
shenko-0.1.90.dist-info/top_level.txt
shenko-0.1.90.dist-info/RECORD
