Metadata-Version: 2.1
Name: shenko
Version: 0.1.90
Summary: visit us at www.shenko.org
Home-page: https://github.com/shenko/shenko
Author: Shenko Development Team
Author-email: Shenko Development Team <shenko.org@gmail.com>
License: GNU General Public License v3
Project-URL: Homepage, https://github.com/shenko/shenko
Keywords: shenko
Classifier: Development Status :: 2 - Pre-Alpha
Classifier: Intended Audience :: Developers
Classifier: License :: OSI Approved :: GNU General Public License v3 (GPLv3)
Classifier: Natural Language :: English
Classifier: Programming Language :: Python :: 3
Classifier: Programming Language :: Python :: 3.4
Classifier: Programming Language :: Python :: 3.5
Classifier: Programming Language :: Python :: 3.6
Requires-Python: >=3.4
License-File: LICENSE
License-File: AUTHORS.rst
Requires-Dist: Click>=6.0
Requires-Dist: panda3d>=1.10.10
